safedelete/__init__.py
safedelete/admin.py
safedelete/apps.py
safedelete/config.py
safedelete/managers.py
safedelete/models.py
safedelete/query.py
safedelete/queryset.py
safedelete/signals.py
safedelete/utils.py
safedelete/tests/__init__.py
safedelete/tests/models.py
safedelete/tests/settings.py
safedelete/tests/test_admin.py
safedelete/tests/test_custom_queryset.py
safedelete/tests/test_foreignkey.py
safedelete/tests/test_hard_delete.py
safedelete/tests/test_invisible.py
safedelete/tests/test_lookups.py
safedelete/tests/test_many2many.py
safedelete/tests/test_no_cascade.py
safedelete/tests/test_no_delete.py
safedelete/tests/test_prefetch_related.py
safedelete/tests/test_queryset.py
safedelete/tests/test_refresh_from_db.py
safedelete/tests/test_single_delete_call_on_inheritance.py
safedelete/tests/test_soft_delete.py
safedelete/tests/test_soft_delete_cascade.py
safedelete/tests/test_subquery.py
safedelete/tests/test_visible_by_pk.py
safedelete/tests/testcase.py
safedelete/tests/urls.py
django_safe_delete_t-1.0.0.dist-info/LICENSE
django_safe_delete_t-1.0.0.dist-info/METADATA
django_safe_delete_t-1.0.0.dist-info/WHEEL
django_safe_delete_t-1.0.0.dist-info/top_level.txt
django_safe_delete_t-1.0.0.dist-info/RECORD
